[
    {
        "titulo":"",
        "autor":"",
        "genero":""
    },
    {
        "titulo":"",
        "autor":"",
        "genero":""
    },
    {
        "titulo":"",
        "autor":"",
        "genero":""
    },
    {
        "titulo":"",
        "autor":"",
        "genero":""
    },
    {
        "titulo":"",
        "autor":"",
        "genero":""
    },
    {
        "titulo":"",
        "autor":"",
        "genero":""
    },
    {
        "titulo":"",
        "autor":"",
        "genero":""
    },
    {
        "titulo":"",
        "autor":"",
        "genero":""
    },
    {
        "titulo":"",
        "autor":"",
        "genero":""
    },
    {
        "titulo":"",
        "autor":"",
        "genero":""
    }
]